octopus_discord/__init__.py
octopus_discord/discord_chat.py
octopus_terminal/__init__.py
octopus_terminal/markdown.py
octopus_terminal/ping.py
octopus_terminal/terminal_chat.py
octopus_terminal/utils.py
octopus_chat-0.4.18.dist-info/METADATA
octopus_chat-0.4.18.dist-info/WHEEL
octopus_chat-0.4.18.dist-info/entry_points.txt
octopus_chat-0.4.18.dist-info/top_level.txt
octopus_chat-0.4.18.dist-info/RECORD
