Metadata-Version: 2.1
Name: octopus-chat
Version: 0.4.18
Summary: the chat client for open source code interpreter octopus
Home-page: https://github.com/dbpunk-labs/octopus
Author: imotai
Author-email: wangtaize@dbpunk.com
Requires-Dist: octopus-sdk >=0.1.0
Requires-Dist: rich >=13.5.2
Requires-Dist: prompt-toolkit >=3.0.0
Requires-Dist: click >=8.0.0
Requires-Dist: discord.py >=2.3.2
Requires-Dist: clipboard >=0.0.4
Requires-Dist: term-image >=0.7.0
Requires-Dist: python-dotenv
